deepspectrumlite/__init__.py
deepspectrumlite/__main__.py
deepspectrumlite/cli/__init__.py
deepspectrumlite/cli/convert.py
deepspectrumlite/cli/create_preprocessor.py
deepspectrumlite/cli/devel_test.py
deepspectrumlite/cli/predict.py
deepspectrumlite/cli/stats.py
deepspectrumlite/cli/tflite_stats.py
deepspectrumlite/cli/train.py
deepspectrumlite/cli/utils.py
deepspectrumlite/lib/__init__.py
deepspectrumlite/lib/hyperparameter.py
deepspectrumlite/lib/data/__init__.py
deepspectrumlite/lib/data/data_pipeline.py
deepspectrumlite/lib/data/embedded/__init__.py
deepspectrumlite/lib/data/embedded/preprocessor.py
deepspectrumlite/lib/data/parser/ComParEParser.py
deepspectrumlite/lib/data/parser/__init__.py
deepspectrumlite/lib/data/plot/__init__.py
deepspectrumlite/lib/data/plot/colormap.py
deepspectrumlite/lib/data/plot/color_maps/__init__.py
deepspectrumlite/lib/data/plot/color_maps/abstract_colormap.py
deepspectrumlite/lib/data/plot/color_maps/cividis.py
deepspectrumlite/lib/data/plot/color_maps/inferno.py
deepspectrumlite/lib/data/plot/color_maps/magma.py
deepspectrumlite/lib/data/plot/color_maps/plasma.py
deepspectrumlite/lib/data/plot/color_maps/viridis.py
deepspectrumlite/lib/model/TransferBaseModel.py
deepspectrumlite/lib/model/__init__.py
deepspectrumlite/lib/model/ai_model.py
deepspectrumlite/lib/model/config/__init__.py
deepspectrumlite/lib/model/config/gridsearch.py
deepspectrumlite/lib/model/modules/__init__.py
deepspectrumlite/lib/model/modules/arelu.py
deepspectrumlite/lib/model/modules/attention_module.py
deepspectrumlite/lib/model/modules/augmentable_model.py
deepspectrumlite/lib/model/modules/squeeze_net.py
deepspectrumlite/lib/util/__init__.py
deepspectrumlite/lib/util/audio_utils.py
DeepSpectrumLite-1.0.2.dist-info/LICENSE
DeepSpectrumLite-1.0.2.dist-info/METADATA
DeepSpectrumLite-1.0.2.dist-info/WHEEL
DeepSpectrumLite-1.0.2.dist-info/entry_points.txt
DeepSpectrumLite-1.0.2.dist-info/namespace_packages.txt
DeepSpectrumLite-1.0.2.dist-info/top_level.txt
DeepSpectrumLite-1.0.2.dist-info/RECORD
