Metadata-Version: 2.1
Name: DeepSpectrumLite
Version: 1.0.2
Summary: UNKNOWN
Home-page: https://github.com/DeepSpectrum/DeepSpectrumLite
Author: Tobias Hübner
Author-email: tobias.huebner@informatik.uni-augsburg.de
License: GPLv3+
Project-URL: Source, https://github.com/DeepSpectrum/DeepSpectrumLite
Project-URL: Tracker, https://github.com/DeepSpectrum/DeepSpectrumLite/issues
Keywords: machine-learning audio-analysis science research
Platform: Any
Classifier: Development Status :: 4 - Beta
Classifier: Environment :: GPU :: NVIDIA CUDA :: 11.0
Classifier: Topic :: Scientific/Engineering :: Artificial Intelligence
Classifier: Intended Audience :: Science/Research
Classifier: License :: OSI Approved :: GNU General Public License v3 (GPLv3)
Classifier: Programming Language :: Python :: 3.8
Requires-Python: ~=3.8.0
Requires-Dist: librosa
Requires-Dist: numba
Requires-Dist: pillow
Requires-Dist: pandas
Requires-Dist: scikit-learn
Requires-Dist: click
Requires-Dist: tensorflow (==2.5.1)
Requires-Dist: tensorboard (==2.5)
Requires-Dist: keras-applications
